[
  {
    "DCODE": "0001",
    "DNAME": "사장실",
    "PDEPT": null,
    "AREA": "포항본사"
  },
  {
    "DCODE": "1000",
    "DNAME": "경영지원부",
    "PDEPT": "0001",
    "AREA": "서울지사"
  },
  {
    "DCODE": "1001",
    "DNAME": "재무관리팀",
    "PDEPT": "1000",
    "AREA": "서울지사"
  },
  {
    "DCODE": "1002",
    "DNAME": "총무팀",
    "PDEPT": "1000",
    "AREA": "서울지사"
  },
  {
    "DCODE": "1003",
    "DNAME": "기술부",
    "PDEPT": "0001",
    "AREA": "포항본사"
  },
  {
    "DCODE": "1004",
    "DNAME": "H/W지원",
    "PDEPT": "1003",
    "AREA": "대전지사"
  },
  {
    "DCODE": "1005",
    "DNAME": "S/W지원",
    "PDEPT": "1003",
    "AREA": "경기지사"
  },
  {
    "DCODE": "1006",
    "DNAME": "영업부",
    "PDEPT": "0001",
    "AREA": "포항본사"
  },
  {
    "DCODE": "1007",
    "DNAME": "영업기획팀",
    "PDEPT": "1006",
    "AREA": "포항본사"
  },
  {
    "DCODE": "1008",
    "DNAME": "영업1팀",
    "PDEPT": "1007",
    "AREA": "부산지사"
  },
  {
    "DCODE": "1009",
    "DNAME": "영업2팀",
    "PDEPT": "1007",
    "AREA": "경기지사"
  },
  {
    "DCODE": "1010",
    "DNAME": "영업3팀",
    "PDEPT": "1007",
    "AREA": "서울지사"
  },
  {
    "DCODE": "1011",
    "DNAME": "영업4팀",
    "PDEPT": "1007",
    "AREA": "울산지사"
  }
]